shivs_per_lib/__init__.py
shivs_per_lib/packages.py
shivs_per_lib-0.2.2.dist-info/LICENSE
shivs_per_lib-0.2.2.dist-info/METADATA
shivs_per_lib-0.2.2.dist-info/WHEEL
shivs_per_lib-0.2.2.dist-info/top_level.txt
shivs_per_lib-0.2.2.dist-info/RECORD
