Metadata-Version: 2.1
Name: shivs_per_lib
Version: 0.2.2
Summary: A personal utility package by Shivsamb Harkare.
Author: Shivsamb Mangalkumar Harkare
Author-email: shivsamb1984@gmail.com
License: MIT
Classifier: Programming Language :: Python :: 3
Classifier: License :: OSI Approved :: MIT License
Classifier: Operating System :: OS Independent
Requires-Python: >=3.6
License-File: LICENSE
